README.md
setup.cfg
setup.py
bestemmie/__init__.py
bestemmie.egg-info/PKG-INFO
bestemmie.egg-info/SOURCES.txt
bestemmie.egg-info/dependency_links.txt
bestemmie.egg-info/requires.txt
bestemmie.egg-info/top_level.txt