Metadata-Version: 1.0
Name: bestemmie
Version: 0.4
Summary: Bestemmie.org API for lazy person
Home-page: https://github.com/Trafitto/bestemmie.org-API
Author: Trafitto
Author-email: develop@trafitto.com
License: MIT
Keywords: bestemmie,api,bestemmie.org
Platform: UNKNOWN
